astrocast/__init__.py
astrocast/analysis.py
astrocast/app_analysis.py
astrocast/app_preparation.py
astrocast/autoencoders.py
astrocast/cli_interfaces.py
astrocast/clustering.py
astrocast/denoising.py
astrocast/detection.py
astrocast/experiments.py
astrocast/helper.py
astrocast/preparation.py
astrocast/reduction.py
astrocast-0.4.2.dist-info/LICENSE
astrocast-0.4.2.dist-info/METADATA
astrocast-0.4.2.dist-info/WHEEL
astrocast-0.4.2.dist-info/entry_points.txt
astrocast-0.4.2.dist-info/RECORD
