Metadata-Version: 2.1
Name: astrocast
Version: 0.4.2
Summary: Package to analyze calcium fluorescence events in astrocytes
Author: Jan Philipp Reising
Author-email: jan.reising@ki.se
Requires-Python: >=3.9,<3.11
Classifier: Programming Language :: Python :: 3
Classifier: Programming Language :: Python :: 3.9
Classifier: Programming Language :: Python :: 3.10
Provides-Extra: all
Provides-Extra: doc
Provides-Extra: testing
Provides-Extra: video-player
Requires-Dist: awkward (>=2.4.2,<3.0.0)
Requires-Dist: build (==0.10.0)
Requires-Dist: climage (>=0.2.0,<0.3.0)
Requires-Dist: colorama (>=0.4.6,<0.5.0)
Requires-Dist: colorcet (>=3.0.1,<4.0.0)
Requires-Dist: czifile (>=2019.7.2,<2020.0.0)
Requires-Dist: dask (>=2023.9.2,<2024.0.0)
Requires-Dist: dask-image (>=2023.8.1,<2024.0.0)
Requires-Dist: datashader (>=0.15.2,<0.16.0)
Requires-Dist: deprecated (>=1.2.14,<2.0.0)
Requires-Dist: deprecation (>=2.1.0,<3.0.0)
Requires-Dist: dtaidistance (>=2.3.10,<3.0.0)
Requires-Dist: fastcluster (>=1.2.6,<2.0.0)
Requires-Dist: gdown (>=4.7.1,<5.0.0)
Requires-Dist: h5py (>=3.9.0,<4.0.0)
Requires-Dist: hdbscan (>=0.8.33,<0.9.0)
Requires-Dist: holoviews (>=1.17.1,<2.0.0)
Requires-Dist: humanize (>=4.8.0,<5.0.0)
Requires-Dist: ipywidgets (>=8.1.1,<9.0.0)
Requires-Dist: jnormcorre (>=0.0.7,<0.0.8)
Requires-Dist: jupyterlab (>=4.0.8,<5.0.0)
Requires-Dist: keras
Requires-Dist: llvmlite (>=0.39,<0.40)
Requires-Dist: matplotlib (>=3.8.0,<4.0.0)
Requires-Dist: multiprocess (>=0.70.15,<0.71.0)
Requires-Dist: napari-plot (>=0.1.5,<0.2.0) ; extra == "video-player" or extra == "all"
Requires-Dist: napari-time-series-plotter ; extra == "video-player" or extra == "all"
Requires-Dist: napari[all] (>=0.4.14,<0.5.0) ; extra == "video-player" or extra == "all"
Requires-Dist: networkx (>=3.1,<4.0)
Requires-Dist: numpy
Requires-Dist: opencv-python (>=4.8.0.76,<5.0.0.0)
Requires-Dist: pandas (>=2.1.0,<3.0.0)
Requires-Dist: peakutils (>=1.3.4,<2.0.0)
Requires-Dist: pointpats (>=2.3.0,<3.0.0)
Requires-Dist: powerlaw (>=1.5,<2.0)
Requires-Dist: prettytable (>=3.9.0,<4.0.0)
Requires-Dist: psutil (>=5.9.5,<6.0.0)
Requires-Dist: pydantic (>=1,<2) ; extra == "video-player" or extra == "all"
Requires-Dist: pyinform (>=0.2.0,<0.3.0)
Requires-Dist: pynwb (>=2.5.0,<3.0.0)
Requires-Dist: pyqt5-qt5 (==5.15.2) ; extra == "video-player" or extra == "all"
Requires-Dist: pytest-cov (>=4.1.0,<5.0.0) ; extra == "testing" or extra == "all"
Requires-Dist: pytest-rerunfailures ; extra == "testing" or extra == "all"
Requires-Dist: pytest-xdist (>=3.3.1,<4.0.0) ; extra == "testing" or extra == "all"
Requires-Dist: pytest[testing] (>=7.4.3,<8.0.0) ; extra == "testing" or extra == "all"
Requires-Dist: pyyaml (>=6.0.1,<7.0.0)
Requires-Dist: scikit-image (>=0.21.0,<0.22.0)
Requires-Dist: scikit-learn (>=1.3.0,<2.0.0)
Requires-Dist: scipy (>=1.11,<2.0)
Requires-Dist: seaborn (>=0.12.2,<0.13.0)
Requires-Dist: shiny (>=0.5.1,<0.6.0)
Requires-Dist: simple-slurm (>=0.2.6,<0.3.0)
Requires-Dist: sphinx (>=7.2.6,<8.0.0) ; extra == "doc" or extra == "all"
Requires-Dist: sphinx-autodoc-typehints (>=1.25.2,<2.0.0) ; extra == "doc" or extra == "all"
Requires-Dist: sphinx-rtd-theme (>=1.3.0,<2.0.0) ; extra == "doc" or extra == "all"
Requires-Dist: tensorflow
Requires-Dist: tensorflow-io-gcs-filesystem (==0.31.0) ; sys_platform == "windows"
Requires-Dist: tifffile (>=2023.8.30,<2024.0.0)
Requires-Dist: tiledb (>=0.23.0,<0.24.0)
Requires-Dist: torch (==2.0.0)
Requires-Dist: tqdm (>=4.66.1,<5.0.0)
Requires-Dist: tsfresh (>=0.20.1,<0.21.0)
Requires-Dist: tslearn (>=0.6.2,<0.7.0)
Requires-Dist: umap-learn ; sys_platform == "linux"
Requires-Dist: umap-learn ; sys_platform == "windows"
Requires-Dist: xarray (>=2023.8.0,<2024.0.0)
Requires-Dist: xxhash (>=3.3.0,<4.0.0)
